README.md
setup.py
pykeeb/__init__.py
pykeeb/keyboard_arc.py
pykeeb/keyboard_matrix.py
pykeeb/keyswitch_mount.py
pykeeb/pykeeb.py
pykeeb.egg-info/PKG-INFO
pykeeb.egg-info/SOURCES.txt
pykeeb.egg-info/dependency_links.txt
pykeeb.egg-info/not-zip-safe
pykeeb.egg-info/top_level.txt
pykeeb/models/cherry.stl
pykeeb/models/dsa_1u.stl
pykeeb/models/matias.stl