Metadata-Version: 1.0
Name: pykeeb
Version: 0.1.1
Summary: Python library to help generate OpenSCAD models of mechanical keyboard plates.
Home-page: http://github.com/raycewest/pykeeb
Author: Rayce West
Author-email: rwest@g.clemson.edu
License: MIT
Platform: UNKNOWN
